sicret.py
sicret-0.1.1.dist-info/LICENSE
sicret-0.1.1.dist-info/METADATA
sicret-0.1.1.dist-info/WHEEL
sicret-0.1.1.dist-info/entry_points.txt
sicret-0.1.1.dist-info/RECORD
