Metadata-Version: 2.1
Name: sicret
Version: 0.1.1
Summary: What happens in secret, stays in sicret.
Author: Rafael Izidoro
Author-email: izidoro.rafa@gmail.com
Requires-Python: >=3.9,<4.0
Classifier: Programming Language :: Python :: 3
Classifier: Programming Language :: Python :: 3.9
Classifier: Programming Language :: Python :: 3.10
Classifier: Programming Language :: Python :: 3.11
Requires-Dist: cryptography (>=41.0.7,<42.0.0)
